streamlit_searchbox/__init__.py
streamlit_searchbox-custom/__init__.py
tests/__init__.py
tests/playwright.py
tests/test_conversion.py
tests/utils.py
streamlit_searchbox_custom-0.1.14.dist-info/LICENSE
streamlit_searchbox_custom-0.1.14.dist-info/METADATA
streamlit_searchbox_custom-0.1.14.dist-info/WHEEL
streamlit_searchbox_custom-0.1.14.dist-info/top_level.txt
streamlit_searchbox_custom-0.1.14.dist-info/RECORD
