Metadata-Version: 2.1
Name: streamlit-searchbox-custom
Version: 0.1.14
Summary: Autocomplete Searchbox
Home-page: https://github.com/m-wrzr/streamlit-searchbox
Author: m-wrzr
Requires-Python: >=3.8, !=3.9.7
License-File: LICENSE
Requires-Dist: streamlit (!=1.37.0,>=1.0)
Provides-Extra: dev
Requires-Dist: pre-commit ; extra == 'dev'
Requires-Dist: black ; extra == 'dev'
Requires-Dist: isort ; extra == 'dev'
Requires-Dist: ruff ; extra == 'dev'
Requires-Dist: pyright ; extra == 'dev'
Provides-Extra: tests
Requires-Dist: wikipedia ; extra == 'tests'
Requires-Dist: pytest ; extra == 'tests'
Requires-Dist: pytest-playwright ; extra == 'tests'
